clbscr/__init__.py
clbscr/maker.py
clbscr-0.1.1.dist-info/LICENSE
clbscr-0.1.1.dist-info/METADATA
clbscr-0.1.1.dist-info/WHEEL
clbscr-0.1.1.dist-info/top_level.txt
clbscr-0.1.1.dist-info/RECORD
