Metadata-Version: 2.1
Name: clbscr
Version: 0.1.1
Summary: A package for doing some useful stuff
Home-page: https://github.com/davegimo/clbscr
Author: Davide Gimondo
Author-email: davegimo@example.com
License: MIT
Keywords: my-package,example,demo
Platform: UNKNOWN
Classifier: Development Status :: 3 - Alpha
Classifier: Intended Audience :: Developers
Classifier: License :: OSI Approved :: MIT License
Classifier: Programming Language :: Python :: 3
Classifier: Programming Language :: Python :: 3.6
Classifier: Programming Language :: Python :: 3.7
Classifier: Programming Language :: Python :: 3.8
Classifier: Programming Language :: Python :: 3.9
Classifier: Programming Language :: Python :: Implementation :: CPython
Classifier: Programming Language :: Python :: Implementation :: PyPy
Requires-Python: >=3.6, <4
